onnxruntime/LICENSE
onnxruntime/Privacy.md
onnxruntime/ThirdPartyNotices.txt
onnxruntime/__init__.py
onnxruntime/backend/__init__.py
onnxruntime/backend/backend.py
onnxruntime/backend/backend_rep.py
onnxruntime/capi/__init__.py
onnxruntime/capi/_ld_preload.py
onnxruntime/capi/_pybind_state.py
onnxruntime/capi/build_and_package_info.py
onnxruntime/capi/convert_npz_to_onnx_adapter.py
onnxruntime/capi/libonnxruntime.so.1.23.1
onnxruntime/capi/libonnxruntime_providers_cann.so
onnxruntime/capi/libonnxruntime_providers_shared.so
onnxruntime/capi/onnxruntime_collect_build_info.py
onnxruntime/capi/onnxruntime_inference_collection.py
onnxruntime/capi/onnxruntime_pybind11_state.cpython-311-aarch64-linux-gnu.so
onnxruntime/capi/onnxruntime_validation.py
onnxruntime/datasets/__init__.py
onnxruntime/datasets/logreg_iris.onnx
onnxruntime/datasets/mul_1.onnx
onnxruntime/datasets/sigmoid.onnx
onnxruntime/quantization/__init__.py
onnxruntime/quantization/base_quantizer.py
onnxruntime/quantization/calibrate.py
onnxruntime/quantization/matmul_bnb4_quantizer.py
onnxruntime/quantization/matmul_nbits_quantizer.py
onnxruntime/quantization/onnx_model.py
onnxruntime/quantization/onnx_quantizer.py
onnxruntime/quantization/preprocess.py
onnxruntime/quantization/qdq_loss_debug.py
onnxruntime/quantization/qdq_quantizer.py
onnxruntime/quantization/quant_utils.py
onnxruntime/quantization/quantize.py
onnxruntime/quantization/registry.py
onnxruntime/quantization/shape_inference.py
onnxruntime/quantization/static_quantize_runner.py
onnxruntime/quantization/tensor_quant_overrides.py
onnxruntime/quantization/CalTableFlatBuffers/KeyValue.py
onnxruntime/quantization/CalTableFlatBuffers/TrtTable.py
onnxruntime/quantization/CalTableFlatBuffers/__init__.py
onnxruntime/quantization/execution_providers/qnn/__init__.py
onnxruntime/quantization/execution_providers/qnn/fusion_lpnorm.py
onnxruntime/quantization/execution_providers/qnn/fusion_spacetodepth.py
onnxruntime_cann-1.23.1.dist-info/METADATA
onnxruntime_cann-1.23.1.dist-info/WHEEL
onnxruntime_cann-1.23.1.dist-info/entry_points.txt
onnxruntime_cann-1.23.1.dist-info/top_level.txt
onnxruntime_cann-1.23.1.dist-info/RECORD
